mcmaps/__init__.py
mcmaps/generate_gallery.py
mcmaps/version.py
mcmaps/__pycache__/__init__.cpython-312.pyc
mcmaps/data/BlueDarkRed18.txt
mcmaps/data/SunShine12.txt
mcmaps/data/SyedSpectral.txt
mcmaps/source/_static/colormap_gallery.html
mcmaps-1.0.0.dist-info/METADATA
mcmaps-1.0.0.dist-info/WHEEL
mcmaps-1.0.0.dist-info/entry_points.txt
mcmaps-1.0.0.dist-info/top_level.txt
mcmaps-1.0.0.dist-info/RECORD
