Metadata-Version: 2.4
Name: mcmaps
Version: 1.0.0
Summary: A package providing custom colormaps
Author-email: Hamid Ali Syed <hamidsyed37@gmail.com>
Maintainer-email: Hamid Ali Syed <hamidsyed37@gmail.com>
License-Expression: MIT
Project-URL: Homepage, https://github.com/syedhamidali/mcmaps
Requires-Python: >=3.7
Provides-Extra: dev
Requires-Dist: pytest; extra == "dev"
Requires-Dist: pytest-cov; extra == "dev"
Requires-Dist: ruff; extra == "dev"
Requires-Dist: black; extra == "dev"
Requires-Dist: pre-commit; extra == "dev"
Requires-Dist: coverage; extra == "dev"
Provides-Extra: docs
Requires-Dist: sphinx; extra == "docs"
Requires-Dist: sphinx-gallery; extra == "docs"
Requires-Dist: pydata-sphinx-theme; extra == "docs"
Requires-Dist: numpydoc; extra == "docs"
Requires-Dist: myst-parser; extra == "docs"
Requires-Dist: matplotlib; extra == "docs"
Requires-Dist: numpy; extra == "docs"
Requires-Dist: pandas; extra == "docs"
Requires-Dist: scipy; extra == "docs"
